fancyflags/__init__.py
fancyflags/_argument_parsers.py
fancyflags/_argument_parsers_test.py
fancyflags/_auto.py
fancyflags/_auto_test.py
fancyflags/_define_auto.py
fancyflags/_define_auto_test.py
fancyflags/_definitions.py
fancyflags/_definitions_test.py
fancyflags/_flags.py
fancyflags/_flags_test.py
fancyflags/_flagsaver_test.py
fancyflags/_metadata.py
fancyflags-1.2.dist-info/LICENSE
fancyflags-1.2.dist-info/METADATA
fancyflags-1.2.dist-info/WHEEL
fancyflags-1.2.dist-info/top_level.txt
fancyflags-1.2.dist-info/RECORD
